{
  "openapi": "3.0.1",
  "info": {
    "title": "ERP Backend API",
    "version": "v1"
  },
  "paths": {
    "/api/Addons": {
      "get": {
        "tags": [
          "Addons"
        ],
        "responses": {
          "200": {
            "description": "OK",
            "content": {
              "text/plain": {
                "schema": {
                  "type": "array",
                  "items": {
                    "$ref": "#/components/schemas/Addon"
                  }
                }
              },
              "application/json": {
                "schema": {
                  "type": "array",
                  "items": {
                    "$ref": "#/components/schemas/Addon"
                  }
                }
              },
              "text/json": {
                "schema": {
                  "type": "array",
                  "items": {
                    "$ref": "#/components/schemas/Addon"
                  }
                }
              }
            }
          }
        }
      },
      "post": {
        "tags": [
          "Addons"
        ],
        "requestBody": {
          "content": {
            "application/json": {
              "schema": {
                "$ref": "#/components/schemas/Addon"
              }
            },
            "text/json": {
              "schema": {
                "$ref": "#/components/schemas/Addon"
              }
            },
            "application/*+json": {
              "schema": {
                "$ref": "#/components/schemas/Addon"
              }
            }
          }
        },
        "responses": {
          "200": {
            "description": "OK",
            "content": {
              "text/plain": {
                "schema": {
                  "$ref": "#/components/schemas/Addon"
                }
              },
              "application/json": {
                "schema": {
                  "$ref": "#/components/schemas/Addon"
                }
              },
              "text/json": {
                "schema": {
                  "$ref": "#/components/schemas/Addon"
                }
              }
            }
          }
        }
      }
    },
    "/api/Addons/active": {
      "get": {
        "tags": [
          "Addons"
        ],
        "responses": {
          "200": {
            "description": "OK",
            "content": {
              "text/plain": {
                "schema": {
                  "type": "array",
                  "items": {
                    "$ref": "#/components/schemas/Addon"
                  }
                }
              },
              "application/json": {
                "schema": {
                  "type": "array",
                  "items": {
                    "$ref": "#/components/schemas/Addon"
                  }
                }
              },
              "text/json": {
                "schema": {
                  "type": "array",
                  "items": {
                    "$ref": "#/components/schemas/Addon"
                  }
                }
              }
            }
          }
        }
      }
    },
    "/api/Addons/by-type/{type}": {
      "get": {
        "tags": [
          "Addons"
        ],
        "parameters": [
          {
            "name": "type",
            "in": "path",
            "required": true,
            "schema": {
              "type": "string"
            }
          }
        ],
        "responses": {
          "200": {
            "description": "OK",
            "content": {
              "text/plain": {
                "schema": {
                  "type": "array",
                  "items": {
                    "$ref": "#/components/schemas/Addon"
                  }
                }
              },
              "application/json": {
                "schema": {
                  "type": "array",
                  "items": {
                    "$ref": "#/components/schemas/Addon"
                  }
                }
              },
              "text/json": {
                "schema": {
                  "type": "array",
                  "items": {
                    "$ref": "#/components/schemas/Addon"
                  }
                }
              }
            }
          }
        }
      }
    },
    "/api/Addons/{id}": {
      "get": {
        "tags": [
          "Addons"
        ],
        "parameters": [
          {
            "name": "id",
            "in": "path",
            "required": true,
            "schema": {
              "type": "integer",
              "format": "int32"
            }
          }
        ],
        "responses": {
          "200": {
            "description": "OK",
            "content": {
              "text/plain": {
                "schema": {
                  "$ref": "#/components/schemas/Addon"
                }
              },
              "application/json": {
                "schema": {
                  "$ref": "#/components/schemas/Addon"
                }
              },
              "text/json": {
                "schema": {
                  "$ref": "#/components/schemas/Addon"
                }
              }
            }
          }
        }
      },
      "put": {
        "tags": [
          "Addons"
        ],
        "parameters": [
          {
            "name": "id",
            "in": "path",
            "required": true,
            "schema": {
              "type": "integer",
              "format": "int32"
            }
          }
        ],
        "requestBody": {
          "content": {
            "application/json": {
              "schema": {
                "type": "object",
                "additionalProperties": { }
              }
            },
            "text/json": {
              "schema": {
                "type": "object",
                "additionalProperties": { }
              }
            },
            "application/*+json": {
              "schema": {
                "type": "object",
                "additionalProperties": { }
              }
            }
          }
        },
        "responses": {
          "200": {
            "description": "OK",
            "content": {
              "text/plain": {
                "schema": {
                  "$ref": "#/components/schemas/UpdateAddonResponse"
                }
              },
              "application/json": {
                "schema": {
                  "$ref": "#/components/schemas/UpdateAddonResponse"
                }
              },
              "text/json": {
                "schema": {
                  "$ref": "#/components/schemas/UpdateAddonResponse"
                }
              }
            }
          }
        }
      },
      "delete": {
        "tags": [
          "Addons"
        ],
        "parameters": [
          {
            "name": "id",
            "in": "path",
            "required": true,
            "schema": {
              "type": "integer",
              "format": "int32"
            }
          }
        ],
        "responses": {
          "200": {
            "description": "OK",
            "content": {
              "text/plain": {
                "schema": {
                  "$ref": "#/components/schemas/DeleteAddonResponse"
                }
              },
              "application/json": {
                "schema": {
                  "$ref": "#/components/schemas/DeleteAddonResponse"
                }
              },
              "text/json": {
                "schema": {
                  "$ref": "#/components/schemas/DeleteAddonResponse"
                }
              }
            }
          }
        }
      }
    },
    "/api/Auth/login": {
      "post": {
        "tags": [
          "Auth"
        ],
        "requestBody": {
          "content": {
            "application/json": {
              "schema": {
                "$ref": "#/components/schemas/LoginRequest"
              }
            },
            "text/json": {
              "schema": {
                "$ref": "#/components/schemas/LoginRequest"
              }
            },
            "application/*+json": {
              "schema": {
                "$ref": "#/components/schemas/LoginRequest"
              }
            }
          }
        },
        "responses": {
          "200": {
            "description": "OK"
          }
        }
      }
    },
    "/api/Auth/refresh-token": {
      "post": {
        "tags": [
          "Auth"
        ],
        "responses": {
          "200": {
            "description": "OK"
          }
        }
      }
    },
    "/api/Auth/logout": {
      "post": {
        "tags": [
          "Auth"
        ],
        "responses": {
          "200": {
            "description": "OK"
          }
        }
      }
    },
    "/api/Auth/sessions": {
      "get": {
        "tags": [
          "Auth"
        ],
        "responses": {
          "200": {
            "description": "OK",
            "content": {
              "text/plain": {
                "schema": {
                  "type": "array",
                  "items": {
                    "$ref": "#/components/schemas/SessionInfo"
                  }
                }
              },
              "application/json": {
                "schema": {
                  "type": "array",
                  "items": {
                    "$ref": "#/components/schemas/SessionInfo"
                  }
                }
              },
              "text/json": {
                "schema": {
                  "type": "array",
                  "items": {
                    "$ref": "#/components/schemas/SessionInfo"
                  }
                }
              }
            }
          }
        }
      }
    },
    "/api/Auth/revoke-session/{id}": {
      "post": {
        "tags": [
          "Auth"
        ],
        "parameters": [
          {
            "name": "id",
            "in": "path",
            "required": true,
            "schema": {
              "type": "integer",
              "format": "int32"
            }
          }
        ],
        "responses": {
          "200": {
            "description": "OK"
          }
        }
      }
    },
    "/api/Auth/revoke-all-sessions": {
      "post": {
        "tags": [
          "Auth"
        ],
        "responses": {
          "200": {
            "description": "OK"
          }
        }
      }
    },
    "/api/Customers": {
      "get": {
        "tags": [
          "Customers"
        ],
        "responses": {
          "200": {
            "description": "OK",
            "content": {
              "text/plain": {
                "schema": {
                  "type": "array",
                  "items": {
                    "$ref": "#/components/schemas/Customer"
                  }
                }
              },
              "application/json": {
                "schema": {
                  "type": "array",
                  "items": {
                    "$ref": "#/components/schemas/Customer"
                  }
                }
              },
              "text/json": {
                "schema": {
                  "type": "array",
                  "items": {
                    "$ref": "#/components/schemas/Customer"
                  }
                }
              }
            }
          }
        }
      },
      "post": {
        "tags": [
          "Customers"
        ],
        "requestBody": {
          "content": {
            "application/json": {
              "schema": {
                "$ref": "#/components/schemas/Customer"
              }
            },
            "text/json": {
              "schema": {
                "$ref": "#/components/schemas/Customer"
              }
            },
            "application/*+json": {
              "schema": {
                "$ref": "#/components/schemas/Customer"
              }
            }
          }
        },
        "responses": {
          "200": {
            "description": "OK",
            "content": {
              "text/plain": {
                "schema": {
                  "$ref": "#/components/schemas/Customer"
                }
              },
              "application/json": {
                "schema": {
                  "$ref": "#/components/schemas/Customer"
                }
              },
              "text/json": {
                "schema": {
                  "$ref": "#/components/schemas/Customer"
                }
              }
            }
          }
        }
      }
    },
    "/api/Customers/active": {
      "get": {
        "tags": [
          "Customers"
        ],
        "responses": {
          "200": {
            "description": "OK",
            "content": {
              "text/plain": {
                "schema": {
                  "type": "array",
                  "items": {
                    "$ref": "#/components/schemas/Customer"
                  }
                }
              },
              "application/json": {
                "schema": {
                  "type": "array",
                  "items": {
                    "$ref": "#/components/schemas/Customer"
                  }
                }
              },
              "text/json": {
                "schema": {
                  "type": "array",
                  "items": {
                    "$ref": "#/components/schemas/Customer"
                  }
                }
              }
            }
          }
        }
      }
    },
    "/api/Customers/{id}": {
      "get": {
        "tags": [
          "Customers"
        ],
        "parameters": [
          {
            "name": "id",
            "in": "path",
            "required": true,
            "schema": {
              "type": "integer",
              "format": "int32"
            }
          }
        ],
        "responses": {
          "200": {
            "description": "OK",
            "content": {
              "text/plain": {
                "schema": {
                  "$ref": "#/components/schemas/Customer"
                }
              },
              "application/json": {
                "schema": {
                  "$ref": "#/components/schemas/Customer"
                }
              },
              "text/json": {
                "schema": {
                  "$ref": "#/components/schemas/Customer"
                }
              }
            }
          }
        }
      },
      "put": {
        "tags": [
          "Customers"
        ],
        "parameters": [
          {
            "name": "id",
            "in": "path",
            "required": true,
            "schema": {
              "type": "integer",
              "format": "int32"
            }
          }
        ],
        "requestBody": {
          "content": {
            "application/json": {
              "schema": {
                "type": "object",
                "additionalProperties": { }
              }
            },
            "text/json": {
              "schema": {
                "type": "object",
                "additionalProperties": { }
              }
            },
            "application/*+json": {
              "schema": {
                "type": "object",
                "additionalProperties": { }
              }
            }
          }
        },
        "responses": {
          "200": {
            "description": "OK",
            "content": {
              "text/plain": {
                "schema": {
                  "$ref": "#/components/schemas/UpdateCustomerResponse"
                }
              },
              "application/json": {
                "schema": {
                  "$ref": "#/components/schemas/UpdateCustomerResponse"
                }
              },
              "text/json": {
                "schema": {
                  "$ref": "#/components/schemas/UpdateCustomerResponse"
                }
              }
            }
          }
        }
      },
      "patch": {
        "tags": [
          "Customers"
        ],
        "parameters": [
          {
            "name": "id",
            "in": "path",
            "required": true,
            "schema": {
              "type": "integer",
              "format": "int32"
            }
          }
        ],
        "requestBody": {
          "content": {
            "application/json": {
              "schema": {
                "type": "object",
                "additionalProperties": { }
              }
            },
            "text/json": {
              "schema": {
                "type": "object",
                "additionalProperties": { }
              }
            },
            "application/*+json": {
              "schema": {
                "type": "object",
                "additionalProperties": { }
              }
            }
          }
        },
        "responses": {
          "200": {
            "description": "OK"
          }
        }
      },
      "delete": {
        "tags": [
          "Customers"
        ],
        "parameters": [
          {
            "name": "id",
            "in": "path",
            "required": true,
            "schema": {
              "type": "integer",
              "format": "int32"
            }
          }
        ],
        "responses": {
          "200": {
            "description": "OK",
            "content": {
              "text/plain": {
                "schema": {
                  "$ref": "#/components/schemas/DeleteCustomerResponse"
                }
              },
              "application/json": {
                "schema": {
                  "$ref": "#/components/schemas/DeleteCustomerResponse"
                }
              },
              "text/json": {
                "schema": {
                  "$ref": "#/components/schemas/DeleteCustomerResponse"
                }
              }
            }
          }
        }
      }
    },
    "/api/Customers/{id}/toggle-status": {
      "patch": {
        "tags": [
          "Customers"
        ],
        "parameters": [
          {
            "name": "id",
            "in": "path",
            "required": true,
            "schema": {
              "type": "integer",
              "format": "int32"
            }
          }
        ],
        "responses": {
          "200": {
            "description": "OK"
          }
        }
      }
    },
    "/api/Customers/by-type/{customerType}": {
      "get": {
        "tags": [
          "Customers"
        ],
        "parameters": [
          {
            "name": "customerType",
            "in": "path",
            "required": true,
            "schema": {
              "type": "string"
            }
          }
        ],
        "responses": {
          "200": {
            "description": "OK",
            "content": {
              "text/plain": {
                "schema": {
                  "type": "array",
                  "items": {
                    "$ref": "#/components/schemas/Customer"
                  }
                }
              },
              "application/json": {
                "schema": {
                  "type": "array",
                  "items": {
                    "$ref": "#/components/schemas/Customer"
                  }
                }
              },
              "text/json": {
                "schema": {
                  "type": "array",
                  "items": {
                    "$ref": "#/components/schemas/Customer"
                  }
                }
              }
            }
          }
        }
      }
    },
    "/api/Customers/type-statistics": {
      "get": {
        "tags": [
          "Customers"
        ],
        "responses": {
          "200": {
            "description": "OK"
          }
        }
      }
    },
    "/api/Customers/individuals": {
      "get": {
        "tags": [
          "Customers"
        ],
        "responses": {
          "200": {
            "description": "OK",
            "content": {
              "text/plain": {
                "schema": {
                  "type": "array",
                  "items": {
                    "$ref": "#/components/schemas/Customer"
                  }
                }
              },
              "application/json": {
                "schema": {
                  "type": "array",
                  "items": {
                    "$ref": "#/components/schemas/Customer"
                  }
                }
              },
              "text/json": {
                "schema": {
                  "type": "array",
                  "items": {
                    "$ref": "#/components/schemas/Customer"
                  }
                }
              }
            }
          }
        }
      }
    },
    "/api/Customers/companies": {
      "get": {
        "tags": [
          "Customers"
        ],
        "responses": {
          "200": {
            "description": "OK",
            "content": {
              "text/plain": {
                "schema": {
                  "type": "array",
                  "items": {
                    "$ref": "#/components/schemas/Customer"
                  }
                }
              },
              "application/json": {
                "schema": {
                  "type": "array",
                  "items": {
                    "$ref": "#/components/schemas/Customer"
                  }
                }
              },
              "text/json": {
                "schema": {
                  "type": "array",
                  "items": {
                    "$ref": "#/components/schemas/Customer"
                  }
                }
              }
            }
          }
        }
      }
    },
    "/api/SaleOrders": {
      "get": {
        "tags": [
          "SaleOrders"
        ],
        "responses": {
          "200": {
            "description": "OK",
            "content": {
              "text/plain": {
                "schema": {
                  "type": "array",
                  "items": {
                    "$ref": "#/components/schemas/SaleOrder"
                  }
                }
              },
              "application/json": {
                "schema": {
                  "type": "array",
                  "items": {
                    "$ref": "#/components/schemas/SaleOrder"
                  }
                }
              },
              "text/json": {
                "schema": {
                  "type": "array",
                  "items": {
                    "$ref": "#/components/schemas/SaleOrder"
                  }
                }
              }
            }
          }
        }
      },
      "post": {
        "tags": [
          "SaleOrders"
        ],
        "requestBody": {
          "content": {
            "application/json": {
              "schema": {
                "$ref": "#/components/schemas/SaleOrder"
              }
            },
            "text/json": {
              "schema": {
                "$ref": "#/components/schemas/SaleOrder"
              }
            },
            "application/*+json": {
              "schema": {
                "$ref": "#/components/schemas/SaleOrder"
              }
            }
          }
        },
        "responses": {
          "200": {
            "description": "OK",
            "content": {
              "text/plain": {
                "schema": {
                  "$ref": "#/components/schemas/SaleOrder"
                }
              },
              "application/json": {
                "schema": {
                  "$ref": "#/components/schemas/SaleOrder"
                }
              },
              "text/json": {
                "schema": {
                  "$ref": "#/components/schemas/SaleOrder"
                }
              }
            }
          }
        }
      }
    },
    "/api/SaleOrders/by-customer/{customerId}": {
      "get": {
        "tags": [
          "SaleOrders"
        ],
        "parameters": [
          {
            "name": "customerId",
            "in": "path",
            "required": true,
            "schema": {
              "type": "integer",
              "format": "int32"
            }
          }
        ],
        "responses": {
          "200": {
            "description": "OK",
            "content": {
              "text/plain": {
                "schema": {
                  "type": "array",
                  "items": {
                    "$ref": "#/components/schemas/SaleOrder"
                  }
                }
              },
              "application/json": {
                "schema": {
                  "type": "array",
                  "items": {
                    "$ref": "#/components/schemas/SaleOrder"
                  }
                }
              },
              "text/json": {
                "schema": {
                  "type": "array",
                  "items": {
                    "$ref": "#/components/schemas/SaleOrder"
                  }
                }
              }
            }
          }
        }
      }
    },
    "/api/SaleOrders/statistics": {
      "get": {
        "tags": [
          "SaleOrders"
        ],
        "responses": {
          "200": {
            "description": "OK"
          }
        }
      }
    },
    "/api/SaleOrders/{id}": {
      "get": {
        "tags": [
          "SaleOrders"
        ],
        "parameters": [
          {
            "name": "id",
            "in": "path",
            "required": true,
            "schema": {
              "type": "integer",
              "format": "int32"
            }
          }
        ],
        "responses": {
          "200": {
            "description": "OK",
            "content": {
              "text/plain": {
                "schema": {
                  "$ref": "#/components/schemas/SaleOrder"
                }
              },
              "application/json": {
                "schema": {
                  "$ref": "#/components/schemas/SaleOrder"
                }
              },
              "text/json": {
                "schema": {
                  "$ref": "#/components/schemas/SaleOrder"
                }
              }
            }
          }
        }
      },
      "put": {
        "tags": [
          "SaleOrders"
        ],
        "parameters": [
          {
            "name": "id",
            "in": "path",
            "required": true,
            "schema": {
              "type": "integer",
              "format": "int32"
            }
          }
        ],
        "requestBody": {
          "content": {
            "application/json": {
              "schema": {
                "type": "object",
                "additionalProperties": { }
              }
            },
            "text/json": {
              "schema": {
                "type": "object",
                "additionalProperties": { }
              }
            },
            "application/*+json": {
              "schema": {
                "type": "object",
                "additionalProperties": { }
              }
            }
          }
        },
        "responses": {
          "200": {
            "description": "OK",
            "content": {
              "text/plain": {
                "schema": {
                  "$ref": "#/components/schemas/UpdateSaleOrderResponse"
                }
              },
              "application/json": {
                "schema": {
                  "$ref": "#/components/schemas/UpdateSaleOrderResponse"
                }
              },
              "text/json": {
                "schema": {
                  "$ref": "#/components/schemas/UpdateSaleOrderResponse"
                }
              }
            }
          }
        }
      },
      "delete": {
        "tags": [
          "SaleOrders"
        ],
        "parameters": [
          {
            "name": "id",
            "in": "path",
            "required": true,
            "schema": {
              "type": "integer",
              "format": "int32"
            }
          }
        ],
        "responses": {
          "200": {
            "description": "OK",
            "content": {
              "text/plain": {
                "schema": {
                  "$ref": "#/components/schemas/DeleteSaleOrderResponse"
                }
              },
              "application/json": {
                "schema": {
                  "$ref": "#/components/schemas/DeleteSaleOrderResponse"
                }
              },
              "text/json": {
                "schema": {
                  "$ref": "#/components/schemas/DeleteSaleOrderResponse"
                }
              }
            }
          }
        }
      }
    },
    "/api/SaleOrders/{id}/probability": {
      "patch": {
        "tags": [
          "SaleOrders"
        ],
        "parameters": [
          {
            "name": "id",
            "in": "path",
            "required": true,
            "schema": {
              "type": "integer",
              "format": "int32"
            }
          }
        ],
        "requestBody": {
          "content": {
            "application/json": {
              "schema": {
                "type": "object",
                "additionalProperties": {
                  "type": "integer",
                  "format": "int32"
                }
              }
            },
            "text/json": {
              "schema": {
                "type": "object",
                "additionalProperties": {
                  "type": "integer",
                  "format": "int32"
                }
              }
            },
            "application/*+json": {
              "schema": {
                "type": "object",
                "additionalProperties": {
                  "type": "integer",
                  "format": "int32"
                }
              }
            }
          }
        },
        "responses": {
          "200": {
            "description": "OK"
          }
        }
      }
    },
    "/api/Services": {
      "get": {
        "tags": [
          "Services"
        ],
        "responses": {
          "200": {
            "description": "OK",
            "content": {
              "text/plain": {
                "schema": {
                  "type": "array",
                  "items": {
                    "$ref": "#/components/schemas/Service"
                  }
                }
              },
              "application/json": {
                "schema": {
                  "type": "array",
                  "items": {
                    "$ref": "#/components/schemas/Service"
                  }
                }
              },
              "text/json": {
                "schema": {
                  "type": "array",
                  "items": {
                    "$ref": "#/components/schemas/Service"
                  }
                }
              }
            }
          }
        }
      },
      "post": {
        "tags": [
          "Services"
        ],
        "requestBody": {
          "content": {
            "application/json": {
              "schema": {
                "$ref": "#/components/schemas/Service"
              }
            },
            "text/json": {
              "schema": {
                "$ref": "#/components/schemas/Service"
              }
            },
            "application/*+json": {
              "schema": {
                "$ref": "#/components/schemas/Service"
              }
            }
          }
        },
        "responses": {
          "200": {
            "description": "OK",
            "content": {
              "text/plain": {
                "schema": {
                  "$ref": "#/components/schemas/Service"
                }
              },
              "application/json": {
                "schema": {
                  "$ref": "#/components/schemas/Service"
                }
              },
              "text/json": {
                "schema": {
                  "$ref": "#/components/schemas/Service"
                }
              }
            }
          }
        }
      }
    },
    "/api/Services/active": {
      "get": {
        "tags": [
          "Services"
        ],
        "responses": {
          "200": {
            "description": "OK",
            "content": {
              "text/plain": {
                "schema": {
                  "type": "array",
                  "items": {
                    "$ref": "#/components/schemas/Service"
                  }
                }
              },
              "application/json": {
                "schema": {
                  "type": "array",
                  "items": {
                    "$ref": "#/components/schemas/Service"
                  }
                }
              },
              "text/json": {
                "schema": {
                  "type": "array",
                  "items": {
                    "$ref": "#/components/schemas/Service"
                  }
                }
              }
            }
          }
        }
      }
    },
    "/api/Services/by-category/{category}": {
      "get": {
        "tags": [
          "Services"
        ],
        "parameters": [
          {
            "name": "category",
            "in": "path",
            "required": true,
            "schema": {
              "type": "string"
            }
          }
        ],
        "responses": {
          "200": {
            "description": "OK",
            "content": {
              "text/plain": {
                "schema": {
                  "type": "array",
                  "items": {
                    "$ref": "#/components/schemas/Service"
                  }
                }
              },
              "application/json": {
                "schema": {
                  "type": "array",
                  "items": {
                    "$ref": "#/components/schemas/Service"
                  }
                }
              },
              "text/json": {
                "schema": {
                  "type": "array",
                  "items": {
                    "$ref": "#/components/schemas/Service"
                  }
                }
              }
            }
          }
        }
      }
    },
    "/api/Services/{id}": {
      "get": {
        "tags": [
          "Services"
        ],
        "parameters": [
          {
            "name": "id",
            "in": "path",
            "required": true,
            "schema": {
              "type": "integer",
              "format": "int32"
            }
          }
        ],
        "responses": {
          "200": {
            "description": "OK",
            "content": {
              "text/plain": {
                "schema": {
                  "$ref": "#/components/schemas/Service"
                }
              },
              "application/json": {
                "schema": {
                  "$ref": "#/components/schemas/Service"
                }
              },
              "text/json": {
                "schema": {
                  "$ref": "#/components/schemas/Service"
                }
              }
            }
          }
        }
      },
      "put": {
        "tags": [
          "Services"
        ],
        "parameters": [
          {
            "name": "id",
            "in": "path",
            "required": true,
            "schema": {
              "type": "integer",
              "format": "int32"
            }
          }
        ],
        "requestBody": {
          "content": {
            "application/json": {
              "schema": {
                "type": "object",
                "additionalProperties": { }
              }
            },
            "text/json": {
              "schema": {
                "type": "object",
                "additionalProperties": { }
              }
            },
            "application/*+json": {
              "schema": {
                "type": "object",
                "additionalProperties": { }
              }
            }
          }
        },
        "responses": {
          "200": {
            "description": "OK",
            "content": {
              "text/plain": {
                "schema": {
                  "$ref": "#/components/schemas/UpdateServiceResponse"
                }
              },
              "application/json": {
                "schema": {
                  "$ref": "#/components/schemas/UpdateServiceResponse"
                }
              },
              "text/json": {
                "schema": {
                  "$ref": "#/components/schemas/UpdateServiceResponse"
                }
              }
            }
          }
        }
      },
      "delete": {
        "tags": [
          "Services"
        ],
        "parameters": [
          {
            "name": "id",
            "in": "path",
            "required": true,
            "schema": {
              "type": "integer",
              "format": "int32"
            }
          }
        ],
        "responses": {
          "200": {
            "description": "OK",
            "content": {
              "text/plain": {
                "schema": {
                  "$ref": "#/components/schemas/DeleteServiceResponse"
                }
              },
              "application/json": {
                "schema": {
                  "$ref": "#/components/schemas/DeleteServiceResponse"
                }
              },
              "text/json": {
                "schema": {
                  "$ref": "#/components/schemas/DeleteServiceResponse"
                }
              }
            }
          }
        }
      }
    },
    "/api/TicketCategories": {
      "get": {
        "tags": [
          "TicketCategories"
        ],
        "responses": {
          "200": {
            "description": "OK"
          }
        }
      },
      "post": {
        "tags": [
          "TicketCategories"
        ],
        "requestBody": {
          "content": {
            "application/json": {
              "schema": {
                "$ref": "#/components/schemas/TicketCategory"
              }
            },
            "text/json": {
              "schema": {
                "$ref": "#/components/schemas/TicketCategory"
              }
            },
            "application/*+json": {
              "schema": {
                "$ref": "#/components/schemas/TicketCategory"
              }
            }
          }
        },
        "responses": {
          "200": {
            "description": "OK"
          }
        }
      }
    },
    "/api/TicketCategories/{id}": {
      "get": {
        "tags": [
          "TicketCategories"
        ],
        "parameters": [
          {
            "name": "id",
            "in": "path",
            "required": true,
            "schema": {
              "type": "integer",
              "format": "int32"
            }
          }
        ],
        "responses": {
          "200": {
            "description": "OK"
          }
        }
      },
      "put": {
        "tags": [
          "TicketCategories"
        ],
        "parameters": [
          {
            "name": "id",
            "in": "path",
            "required": true,
            "schema": {
              "type": "integer",
              "format": "int32"
            }
          }
        ],
        "requestBody": {
          "content": {
            "application/json": {
              "schema": {
                "$ref": "#/components/schemas/TicketCategory"
              }
            },
            "text/json": {
              "schema": {
                "$ref": "#/components/schemas/TicketCategory"
              }
            },
            "application/*+json": {
              "schema": {
                "$ref": "#/components/schemas/TicketCategory"
              }
            }
          }
        },
        "responses": {
          "200": {
            "description": "OK"
          }
        }
      },
      "patch": {
        "tags": [
          "TicketCategories"
        ],
        "parameters": [
          {
            "name": "id",
            "in": "path",
            "required": true,
            "schema": {
              "type": "integer",
              "format": "int32"
            }
          }
        ],
        "requestBody": {
          "content": {
            "application/json": {
              "schema": {
                "$ref": "#/components/schemas/PatchTicketCategoryDto"
              }
            },
            "text/json": {
              "schema": {
                "$ref": "#/components/schemas/PatchTicketCategoryDto"
              }
            },
            "application/*+json": {
              "schema": {
                "$ref": "#/components/schemas/PatchTicketCategoryDto"
              }
            }
          }
        },
        "responses": {
          "200": {
            "description": "OK"
          }
        }
      },
      "delete": {
        "tags": [
          "TicketCategories"
        ],
        "parameters": [
          {
            "name": "id",
            "in": "path",
            "required": true,
            "schema": {
              "type": "integer",
              "format": "int32"
            }
          }
        ],
        "responses": {
          "200": {
            "description": "OK"
          }
        }
      }
    },
    "/api/TicketLogs": {
      "get": {
        "tags": [
          "TicketLogs"
        ],
        "parameters": [
          {
            "name": "ticketId",
            "in": "query",
            "schema": {
              "type": "integer",
              "format": "int32"
            }
          }
        ],
        "responses": {
          "200": {
            "description": "OK",
            "content": {
              "text/plain": {
                "schema": {
                  "type": "array",
                  "items": {
                    "$ref": "#/components/schemas/TicketLog"
                  }
                }
              },
              "application/json": {
                "schema": {
                  "type": "array",
                  "items": {
                    "$ref": "#/components/schemas/TicketLog"
                  }
                }
              },
              "text/json": {
                "schema": {
                  "type": "array",
                  "items": {
                    "$ref": "#/components/schemas/TicketLog"
                  }
                }
              }
            }
          }
        }
      },
      "post": {
        "tags": [
          "TicketLogs"
        ],
        "requestBody": {
          "content": {
            "application/json": {
              "schema": {
                "$ref": "#/components/schemas/TicketLog"
              }
            },
            "text/json": {
              "schema": {
                "$ref": "#/components/schemas/TicketLog"
              }
            },
            "application/*+json": {
              "schema": {
                "$ref": "#/components/schemas/TicketLog"
              }
            }
          }
        },
        "responses": {
          "200": {
            "description": "OK",
            "content": {
              "text/plain": {
                "schema": {
                  "$ref": "#/components/schemas/TicketLog"
                }
              },
              "application/json": {
                "schema": {
                  "$ref": "#/components/schemas/TicketLog"
                }
              },
              "text/json": {
                "schema": {
                  "$ref": "#/components/schemas/TicketLog"
                }
              }
            }
          }
        }
      }
    },
    "/api/TicketLogs/{id}": {
      "get": {
        "tags": [
          "TicketLogs"
        ],
        "parameters": [
          {
            "name": "id",
            "in": "path",
            "required": true,
            "schema": {
              "type": "integer",
              "format": "int32"
            }
          }
        ],
        "responses": {
          "200": {
            "description": "OK",
            "content": {
              "text/plain": {
                "schema": {
                  "$ref": "#/components/schemas/TicketLog"
                }
              },
              "application/json": {
                "schema": {
                  "$ref": "#/components/schemas/TicketLog"
                }
              },
              "text/json": {
                "schema": {
                  "$ref": "#/components/schemas/TicketLog"
                }
              }
            }
          }
        }
      },
      "put": {
        "tags": [
          "TicketLogs"
        ],
        "parameters": [
          {
            "name": "id",
            "in": "path",
            "required": true,
            "schema": {
              "type": "integer",
              "format": "int32"
            }
          }
        ],
        "requestBody": {
          "content": {
            "application/json": {
              "schema": {
                "$ref": "#/components/schemas/TicketLog"
              }
            },
            "text/json": {
              "schema": {
                "$ref": "#/components/schemas/TicketLog"
              }
            },
            "application/*+json": {
              "schema": {
                "$ref": "#/components/schemas/TicketLog"
              }
            }
          }
        },
        "responses": {
          "200": {
            "description": "OK",
            "content": {
              "text/plain": {
                "schema": {
                  "$ref": "#/components/schemas/TicketLog"
                }
              },
              "application/json": {
                "schema": {
                  "$ref": "#/components/schemas/TicketLog"
                }
              },
              "text/json": {
                "schema": {
                  "$ref": "#/components/schemas/TicketLog"
                }
              }
            }
          }
        }
      },
      "delete": {
        "tags": [
          "TicketLogs"
        ],
        "parameters": [
          {
            "name": "id",
            "in": "path",
            "required": true,
            "schema": {
              "type": "integer",
              "format": "int32"
            }
          }
        ],
        "responses": {
          "200": {
            "description": "OK"
          }
        }
      }
    },
    "/api/TicketLogs/by-ticket/{ticketId}": {
      "get": {
        "tags": [
          "TicketLogs"
        ],
        "parameters": [
          {
            "name": "ticketId",
            "in": "path",
            "required": true,
            "schema": {
              "type": "integer",
              "format": "int32"
            }
          }
        ],
        "responses": {
          "200": {
            "description": "OK",
            "content": {
              "text/plain": {
                "schema": {
                  "type": "array",
                  "items": {
                    "$ref": "#/components/schemas/TicketLog"
                  }
                }
              },
              "application/json": {
                "schema": {
                  "type": "array",
                  "items": {
                    "$ref": "#/components/schemas/TicketLog"
                  }
                }
              },
              "text/json": {
                "schema": {
                  "type": "array",
                  "items": {
                    "$ref": "#/components/schemas/TicketLog"
                  }
                }
              }
            }
          }
        }
      }
    },
    "/api/Tickets": {
      "get": {
        "tags": [
          "Tickets"
        ],
        "parameters": [
          {
            "name": "customerId",
            "in": "query",
            "schema": {
              "type": "integer",
              "format": "int32"
            }
          },
          {
            "name": "categoryId",
            "in": "query",
            "schema": {
              "type": "integer",
              "format": "int32"
            }
          },
          {
            "name": "userId",
            "in": "query",
            "schema": {
              "type": "integer",
              "format": "int32"
            }
          },
          {
            "name": "priority",
            "in": "query",
            "schema": {
              "type": "string"
            }
          },
          {
            "name": "status",
            "in": "query",
            "schema": {
              "type": "string"
            }
          },
          {
            "name": "urgencyLevel",
            "in": "query",
            "schema": {
              "type": "integer",
              "format": "int32"
            }
          }
        ],
        "responses": {
          "200": {
            "description": "OK",
            "content": {
              "text/plain": {
                "schema": {
                  "type": "array",
                  "items": {
                    "$ref": "#/components/schemas/Ticket"
                  }
                }
              },
              "application/json": {
                "schema": {
                  "type": "array",
                  "items": {
                    "$ref": "#/components/schemas/Ticket"
                  }
                }
              },
              "text/json": {
                "schema": {
                  "type": "array",
                  "items": {
                    "$ref": "#/components/schemas/Ticket"
                  }
                }
              }
            }
          }
        }
      },
      "post": {
        "tags": [
          "Tickets"
        ],
        "requestBody": {
          "content": {
            "application/json": {
              "schema": {
                "$ref": "#/components/schemas/Ticket"
              }
            },
            "text/json": {
              "schema": {
                "$ref": "#/components/schemas/Ticket"
              }
            },
            "application/*+json": {
              "schema": {
                "$ref": "#/components/schemas/Ticket"
              }
            }
          }
        },
        "responses": {
          "200": {
            "description": "OK",
            "content": {
              "text/plain": {
                "schema": {
                  "$ref": "#/components/schemas/Ticket"
                }
              },
              "application/json": {
                "schema": {
                  "$ref": "#/components/schemas/Ticket"
                }
              },
              "text/json": {
                "schema": {
                  "$ref": "#/components/schemas/Ticket"
                }
              }
            }
          }
        }
      }
    },
    "/api/Tickets/{id}": {
      "get": {
        "tags": [
          "Tickets"
        ],
        "parameters": [
          {
            "name": "id",
            "in": "path",
            "required": true,
            "schema": {
              "type": "integer",
              "format": "int32"
            }
          }
        ],
        "responses": {
          "200": {
            "description": "OK",
            "content": {
              "text/plain": {
                "schema": {
                  "$ref": "#/components/schemas/Ticket"
                }
              },
              "application/json": {
                "schema": {
                  "$ref": "#/components/schemas/Ticket"
                }
              },
              "text/json": {
                "schema": {
                  "$ref": "#/components/schemas/Ticket"
                }
              }
            }
          }
        }
      },
      "put": {
        "tags": [
          "Tickets"
        ],
        "parameters": [
          {
            "name": "id",
            "in": "path",
            "required": true,
            "schema": {
              "type": "integer",
              "format": "int32"
            }
          }
        ],
        "requestBody": {
          "content": {
            "application/json": {
              "schema": {
                "$ref": "#/components/schemas/Ticket"
              }
            },
            "text/json": {
              "schema": {
                "$ref": "#/components/schemas/Ticket"
              }
            },
            "application/*+json": {
              "schema": {
                "$ref": "#/components/schemas/Ticket"
              }
            }
          }
        },
        "responses": {
          "200": {
            "description": "OK"
          }
        }
      },
      "delete": {
        "tags": [
          "Tickets"
        ],
        "parameters": [
          {
            "name": "id",
            "in": "path",
            "required": true,
            "schema": {
              "type": "integer",
              "format": "int32"
            }
          }
        ],
        "responses": {
          "200": {
            "description": "OK"
          }
        }
      }
    },
    "/api/Tickets/{id}/logs": {
      "get": {
        "tags": [
          "Tickets"
        ],
        "parameters": [
          {
            "name": "id",
            "in": "path",
            "required": true,
            "schema": {
              "type": "integer",
              "format": "int32"
            }
          }
        ],
        "responses": {
          "200": {
            "description": "OK",
            "content": {
              "text/plain": {
                "schema": {
                  "type": "array",
                  "items": {
                    "$ref": "#/components/schemas/TicketLog"
                  }
                }
              },
              "application/json": {
                "schema": {
                  "type": "array",
                  "items": {
                    "$ref": "#/components/schemas/TicketLog"
                  }
                }
              },
              "text/json": {
                "schema": {
                  "type": "array",
                  "items": {
                    "$ref": "#/components/schemas/TicketLog"
                  }
                }
              }
            }
          }
        }
      }
    },
    "/api/Tickets/{id}/assign": {
      "put": {
        "tags": [
          "Tickets"
        ],
        "parameters": [
          {
            "name": "id",
            "in": "path",
            "required": true,
            "schema": {
              "type": "integer",
              "format": "int32"
            }
          }
        ],
        "requestBody": {
          "content": {
            "application/json": {
              "schema": {
                "type": "integer",
                "format": "int32"
              }
            },
            "text/json": {
              "schema": {
                "type": "integer",
                "format": "int32"
              }
            },
            "application/*+json": {
              "schema": {
                "type": "integer",
                "format": "int32"
              }
            }
          }
        },
        "responses": {
          "200": {
            "description": "OK"
          }
        }
      }
    },
    "/api/Tickets/{id}/status": {
      "put": {
        "tags": [
          "Tickets"
        ],
        "parameters": [
          {
            "name": "id",
            "in": "path",
            "required": true,
            "schema": {
              "type": "integer",
              "format": "int32"
            }
          }
        ],
        "requestBody": {
          "content": {
            "application/json": {
              "schema": {
                "$ref": "#/components/schemas/UpdateTicketStatusRequest"
              }
            },
            "text/json": {
              "schema": {
                "$ref": "#/components/schemas/UpdateTicketStatusRequest"
              }
            },
            "application/*+json": {
              "schema": {
                "$ref": "#/components/schemas/UpdateTicketStatusRequest"
              }
            }
          }
        },
        "responses": {
          "200": {
            "description": "OK",
            "content": {
              "text/plain": {
                "schema": {
                  "$ref": "#/components/schemas/Ticket"
                }
              },
              "application/json": {
                "schema": {
                  "$ref": "#/components/schemas/Ticket"
                }
              },
              "text/json": {
                "schema": {
                  "$ref": "#/components/schemas/Ticket"
                }
              }
            }
          }
        }
      }
    },
    "/api/Users": {
      "get": {
        "tags": [
          "Users"
        ],
        "responses": {
          "200": {
            "description": "OK",
            "content": {
              "text/plain": {
                "schema": {
                  "type": "array",
                  "items": {
                    "$ref": "#/components/schemas/User"
                  }
                }
              },
              "application/json": {
                "schema": {
                  "type": "array",
                  "items": {
                    "$ref": "#/components/schemas/User"
                  }
                }
              },
              "text/json": {
                "schema": {
                  "type": "array",
                  "items": {
                    "$ref": "#/components/schemas/User"
                  }
                }
              }
            }
          }
        }
      },
      "post": {
        "tags": [
          "Users"
        ],
        "requestBody": {
          "content": {
            "application/json": {
              "schema": {
                "$ref": "#/components/schemas/User"
              }
            },
            "text/json": {
              "schema": {
                "$ref": "#/components/schemas/User"
              }
            },
            "application/*+json": {
              "schema": {
                "$ref": "#/components/schemas/User"
              }
            }
          }
        },
        "responses": {
          "200": {
            "description": "OK",
            "content": {
              "text/plain": {
                "schema": {
                  "$ref": "#/components/schemas/User"
                }
              },
              "application/json": {
                "schema": {
                  "$ref": "#/components/schemas/User"
                }
              },
              "text/json": {
                "schema": {
                  "$ref": "#/components/schemas/User"
                }
              }
            }
          }
        }
      }
    },
    "/api/Users/{id}": {
      "get": {
        "tags": [
          "Users"
        ],
        "parameters": [
          {
            "name": "id",
            "in": "path",
            "required": true,
            "schema": {
              "type": "integer",
              "format": "int32"
            }
          }
        ],
        "responses": {
          "200": {
            "description": "OK",
            "content": {
              "text/plain": {
                "schema": {
                  "$ref": "#/components/schemas/User"
                }
              },
              "application/json": {
                "schema": {
                  "$ref": "#/components/schemas/User"
                }
              },
              "text/json": {
                "schema": {
                  "$ref": "#/components/schemas/User"
                }
              }
            }
          }
        }
      },
      "put": {
        "tags": [
          "Users"
        ],
        "parameters": [
          {
            "name": "id",
            "in": "path",
            "required": true,
            "schema": {
              "type": "integer",
              "format": "int32"
            }
          }
        ],
        "requestBody": {
          "content": {
            "application/json": {
              "schema": {
                "type": "object",
                "additionalProperties": { }
              }
            },
            "text/json": {
              "schema": {
                "type": "object",
                "additionalProperties": { }
              }
            },
            "application/*+json": {
              "schema": {
                "type": "object",
                "additionalProperties": { }
              }
            }
          }
        },
        "responses": {
          "200": {
            "description": "OK",
            "content": {
              "text/plain": {
                "schema": {
                  "$ref": "#/components/schemas/UpdateUserResponse"
                }
              },
              "application/json": {
                "schema": {
                  "$ref": "#/components/schemas/UpdateUserResponse"
                }
              },
              "text/json": {
                "schema": {
                  "$ref": "#/components/schemas/UpdateUserResponse"
                }
              }
            }
          }
        }
      },
      "delete": {
        "tags": [
          "Users"
        ],
        "parameters": [
          {
            "name": "id",
            "in": "path",
            "required": true,
            "schema": {
              "type": "integer",
              "format": "int32"
            }
          }
        ],
        "responses": {
          "200": {
            "description": "OK",
            "content": {
              "text/plain": {
                "schema": {
                  "$ref": "#/components/schemas/DeleteUserResponse"
                }
              },
              "application/json": {
                "schema": {
                  "$ref": "#/components/schemas/DeleteUserResponse"
                }
              },
              "text/json": {
                "schema": {
                  "$ref": "#/components/schemas/DeleteUserResponse"
                }
              }
            }
          }
        }
      }
    }
  },
  "components": {
    "schemas": {
      "Addon": {
        "required": [
          "name",
          "price",
          "quantity"
        ],
        "type": "object",
        "properties": {
          "id": {
            "type": "integer",
            "format": "int32"
          },
          "name": {
            "maxLength": 200,
            "minLength": 0,
            "type": "string"
          },
          "description": {
            "maxLength": 1000,
            "minLength": 0,
            "type": "string",
            "nullable": true
          },
          "price": {
            "minimum": 0,
            "type": "number",
            "format": "double"
          },
          "quantity": {
            "maximum": 2147483647,
            "minimum": 1,
            "type": "integer",
            "format": "int32"
          },
          "type": {
            "maxLength": 50,
            "minLength": 0,
            "type": "string",
            "nullable": true
          },
          "isActive": {
            "type": "boolean"
          },
          "notes": {
            "maxLength": 2000,
            "minLength": 0,
            "type": "string",
            "nullable": true
          },
          "createdAt": {
            "type": "string",
            "format": "date-time"
          },
          "updatedAt": {
            "type": "string",
            "format": "date-time",
            "nullable": true
          }
        },
        "additionalProperties": false
      },
      "AddonInfo": {
        "type": "object",
        "properties": {
          "id": {
            "type": "integer",
            "format": "int32"
          },
          "name": {
            "type": "string",
            "nullable": true
          },
          "description": {
            "type": "string",
            "nullable": true
          },
          "price": {
            "type": "number",
            "format": "double"
          },
          "quantity": {
            "type": "integer",
            "format": "int32"
          },
          "type": {
            "type": "string",
            "nullable": true
          },
          "isActive": {
            "type": "boolean"
          },
          "notes": {
            "type": "string",
            "nullable": true
          }
        },
        "additionalProperties": false
      },
      "Customer": {
        "type": "object",
        "properties": {
          "id": {
            "type": "integer",
            "format": "int32"
          },
          "name": {
            "maxLength": 100,
            "minLength": 0,
            "type": "string",
            "nullable": true
          },
          "address": {
            "maxLength": 500,
            "minLength": 0,
            "type": "string",
            "nullable": true
          },
          "birthDate": {
            "type": "string",
            "format": "date-time",
            "nullable": true
          },
          "idNumber": {
            "maxLength": 50,
            "minLength": 0,
            "type": "string",
            "nullable": true
          },
          "phoneNumber": {
            "maxLength": 20,
            "minLength": 0,
            "type": "string",
            "nullable": true
          },
          "email": {
            "maxLength": 150,
            "minLength": 0,
            "type": "string",
            "format": "email",
            "nullable": true
          },
          "domain": {
            "maxLength": 100,
            "minLength": 0,
            "type": "string",
            "nullable": true
          },
          "companyName": {
            "maxLength": 200,
            "minLength": 0,
            "type": "string",
            "nullable": true
          },
          "companyAddress": {
            "maxLength": 500,
            "minLength": 0,
            "type": "string",
            "nullable": true
          },
          "establishedDate": {
            "type": "string",
            "format": "date-time",
            "nullable": true
          },
          "taxCode": {
            "maxLength": 50,
            "minLength": 0,
            "type": "string",
            "nullable": true
          },
          "companyDomain": {
            "maxLength": 100,
            "minLength": 0,
            "type": "string",
            "nullable": true
          },
          "representativeName": {
            "maxLength": 100,
            "minLength": 0,
            "type": "string",
            "nullable": true
          },
          "representativePosition": {
            "maxLength": 100,
            "minLength": 0,
            "type": "string",
            "nullable": true
          },
          "representativeIdNumber": {
            "maxLength": 50,
            "minLength": 0,
            "type": "string",
            "nullable": true
          },
          "representativePhone": {
            "maxLength": 20,
            "minLength": 0,
            "type": "string",
            "nullable": true
          },
          "representativeEmail": {
            "maxLength": 150,
            "minLength": 0,
            "type": "string",
            "format": "email",
            "nullable": true
          },
          "techContactName": {
            "maxLength": 100,
            "minLength": 0,
            "type": "string",
            "nullable": true
          },
          "techContactPhone": {
            "maxLength": 20,
            "minLength": 0,
            "type": "string",
            "nullable": true
          },
          "techContactEmail": {
            "maxLength": 150,
            "minLength": 0,
            "type": "string",
            "format": "email",
            "nullable": true
          },
          "isActive": {
            "type": "boolean"
          },
          "customerType": {
            "maxLength": 20,
            "minLength": 0,
            "type": "string",
            "nullable": true
          },
          "status": {
            "maxLength": 20,
            "minLength": 0,
            "type": "string",
            "nullable": true
          },
          "notes": {
            "maxLength": 2000,
            "minLength": 0,
            "type": "string",
            "nullable": true
          },
          "createdAt": {
            "type": "string",
            "format": "date-time"
          },
          "updatedAt": {
            "type": "string",
            "format": "date-time",
            "nullable": true
          }
        },
        "additionalProperties": false
      },
      "CustomerInfo": {
        "type": "object",
        "properties": {
          "id": {
            "type": "integer",
            "format": "int32"
          },
          "name": {
            "type": "string",
            "nullable": true
          },
          "email": {
            "type": "string",
            "nullable": true
          },
          "phoneNumber": {
            "type": "string",
            "nullable": true
          },
          "companyName": {
            "type": "string",
            "nullable": true
          },
          "representativeName": {
            "type": "string",
            "nullable": true
          },
          "representativeEmail": {
            "type": "string",
            "nullable": true
          },
          "customerType": {
            "type": "string",
            "nullable": true
          },
          "isActive": {
            "type": "boolean"
          },
          "status": {
            "type": "string",
            "nullable": true
          }
        },
        "additionalProperties": false
      },
      "DeleteAddonResponse": {
        "type": "object",
        "properties": {
          "message": {
            "type": "string",
            "nullable": true
          },
          "deletedAddon": {
            "$ref": "#/components/schemas/AddonInfo"
          },
          "deletedAt": {
            "type": "string",
            "format": "date-time"
          }
        },
        "additionalProperties": false
      },
      "DeleteCustomerResponse": {
        "type": "object",
        "properties": {
          "message": {
            "type": "string",
            "nullable": true
          },
          "deletedCustomer": {
            "$ref": "#/components/schemas/CustomerInfo"
          },
          "deletedAt": {
            "type": "string",
            "format": "date-time"
          }
        },
        "additionalProperties": false
      },
      "DeleteSaleOrderResponse": {
        "type": "object",
        "properties": {
          "message": {
            "type": "string",
            "nullable": true
          },
          "deletedSaleOrder": {
            "$ref": "#/components/schemas/SaleOrderInfo"
          },
          "deletedAt": {
            "type": "string",
            "format": "date-time"
          }
        },
        "additionalProperties": false
      },
      "DeleteServiceResponse": {
        "type": "object",
        "properties": {
          "message": {
            "type": "string",
            "nullable": true
          },
          "deletedService": {
            "$ref": "#/components/schemas/ServiceInfo"
          },
          "deletedAt": {
            "type": "string",
            "format": "date-time"
          }
        },
        "additionalProperties": false
      },
      "DeleteUserResponse": {
        "type": "object",
        "properties": {
          "message": {
            "type": "string",
            "nullable": true
          },
          "deletedUser": {
            "$ref": "#/components/schemas/UserInfo"
          },
          "deletedAt": {
            "type": "string",
            "format": "date-time"
          }
        },
        "additionalProperties": false
      },
      "LoginRequest": {
        "required": [
          "email",
          "password"
        ],
        "type": "object",
        "properties": {
          "email": {
            "minLength": 1,
            "type": "string",
            "format": "email"
          },
          "password": {
            "minLength": 1,
            "type": "string"
          },
          "deviceInfo": {
            "type": "string",
            "nullable": true
          }
        },
        "additionalProperties": false
      },
      "PatchTicketCategoryDto": {
        "type": "object",
        "properties": {
          "name": {
            "maxLength": 100,
            "minLength": 0,
            "type": "string",
            "nullable": true
          }
        },
        "additionalProperties": false
      },
      "SaleOrder": {
        "required": [
          "customerId",
          "title",
          "value"
        ],
        "type": "object",
        "properties": {
          "id": {
            "type": "integer",
            "format": "int32"
          },
          "title": {
            "maxLength": 255,
            "minLength": 0,
            "type": "string"
          },
          "customerId": {
            "type": "integer",
            "format": "int32"
          },
          "value": {
            "minimum": 0,
            "type": "number",
            "format": "double"
          },
          "probability": {
            "maximum": 100,
            "minimum": 0,
            "type": "integer",
            "format": "int32"
          },
          "notes": {
            "maxLength": 2000,
            "minLength": 0,
            "type": "string",
            "nullable": true
          },
          "serviceId": {
            "type": "integer",
            "format": "int32",
            "nullable": true
          },
          "addonId": {
            "type": "integer",
            "format": "int32",
            "nullable": true
          },
          "createdAt": {
            "type": "string",
            "format": "date-time"
          },
          "updatedAt": {
            "type": "string",
            "format": "date-time",
            "nullable": true
          }
        },
        "additionalProperties": false
      },
      "SaleOrderInfo": {
        "type": "object",
        "properties": {
          "id": {
            "type": "integer",
            "format": "int32"
          },
          "title": {
            "type": "string",
            "nullable": true
          },
          "customerId": {
            "type": "integer",
            "format": "int32"
          },
          "value": {
            "type": "number",
            "format": "double"
          },
          "probability": {
            "type": "integer",
            "format": "int32"
          },
          "notes": {
            "type": "string",
            "nullable": true
          },
          "serviceId": {
            "type": "integer",
            "format": "int32",
            "nullable": true
          },
          "addonId": {
            "type": "integer",
            "format": "int32",
            "nullable": true
          }
        },
        "additionalProperties": false
      },
      "Service": {
        "required": [
          "name",
          "price",
          "quantity"
        ],
        "type": "object",
        "properties": {
          "id": {
            "type": "integer",
            "format": "int32"
          },
          "name": {
            "maxLength": 200,
            "minLength": 0,
            "type": "string"
          },
          "description": {
            "maxLength": 1000,
            "minLength": 0,
            "type": "string",
            "nullable": true
          },
          "price": {
            "minimum": 0,
            "type": "number",
            "format": "double"
          },
          "quantity": {
            "maximum": 2147483647,
            "minimum": 1,
            "type": "integer",
            "format": "int32"
          },
          "category": {
            "maxLength": 50,
            "minLength": 0,
            "type": "string",
            "nullable": true
          },
          "isActive": {
            "type": "boolean"
          },
          "notes": {
            "maxLength": 2000,
            "minLength": 0,
            "type": "string",
            "nullable": true
          },
          "createdAt": {
            "type": "string",
            "format": "date-time"
          },
          "updatedAt": {
            "type": "string",
            "format": "date-time",
            "nullable": true
          }
        },
        "additionalProperties": false
      },
      "ServiceInfo": {
        "type": "object",
        "properties": {
          "id": {
            "type": "integer",
            "format": "int32"
          },
          "name": {
            "type": "string",
            "nullable": true
          },
          "description": {
            "type": "string",
            "nullable": true
          },
          "price": {
            "type": "number",
            "format": "double"
          },
          "quantity": {
            "type": "integer",
            "format": "int32"
          },
          "category": {
            "type": "string",
            "nullable": true
          },
          "isActive": {
            "type": "boolean"
          },
          "notes": {
            "type": "string",
            "nullable": true
          }
        },
        "additionalProperties": false
      },
      "SessionInfo": {
        "type": "object",
        "properties": {
          "id": {
            "type": "integer",
            "format": "int32"
          },
          "deviceInfo": {
            "type": "string",
            "nullable": true
          },
          "ipAddress": {
            "type": "string",
            "nullable": true
          },
          "createdAt": {
            "type": "string",
            "format": "date-time"
          },
          "expiresAt": {
            "type": "string",
            "format": "date-time"
          },
          "isCurrentSession": {
            "type": "boolean"
          }
        },
        "additionalProperties": false
      },
      "Ticket": {
        "required": [
          "categoryId",
          "customerId",
          "description",
          "title"
        ],
        "type": "object",
        "properties": {
          "id": {
            "type": "integer",
            "format": "int32"
          },
          "title": {
            "maxLength": 500,
            "minLength": 0,
            "type": "string"
          },
          "description": {
            "minLength": 1,
            "type": "string"
          },
          "customerId": {
            "type": "integer",
            "format": "int32"
          },
          "customer": {
            "$ref": "#/components/schemas/Customer"
          },
          "priority": {
            "type": "string",
            "nullable": true
          },
          "status": {
            "type": "string",
            "nullable": true
          },
          "categoryId": {
            "type": "integer",
            "format": "int32"
          },
          "category": {
            "$ref": "#/components/schemas/TicketCategory"
          },
          "urgencyLevel": {
            "maximum": 5,
            "minimum": 1,
            "type": "integer",
            "format": "int32"
          },
          "userId": {
            "type": "integer",
            "format": "int32",
            "nullable": true
          },
          "assignedTo": {
            "$ref": "#/components/schemas/User"
          },
          "createdById": {
            "type": "integer",
            "format": "int32",
            "nullable": true
          },
          "createdBy": {
            "$ref": "#/components/schemas/User"
          },
          "deadline": {
            "type": "string",
            "format": "date-time",
            "nullable": true
          },
          "closedAt": {
            "type": "string",
            "format": "date-time",
            "nullable": true
          },
          "createdAt": {
            "type": "string",
            "format": "date-time"
          },
          "updatedAt": {
            "type": "string",
            "format": "date-time",
            "nullable": true
          }
        },
        "additionalProperties": false
      },
      "TicketCategory": {
        "required": [
          "name"
        ],
        "type": "object",
        "properties": {
          "id": {
            "type": "integer",
            "format": "int32"
          },
          "name": {
            "maxLength": 100,
            "minLength": 0,
            "type": "string"
          },
          "createdAt": {
            "type": "string",
            "format": "date-time"
          },
          "updatedAt": {
            "type": "string",
            "format": "date-time",
            "nullable": true
          }
        },
        "additionalProperties": false
      },
      "TicketLog": {
        "required": [
          "content",
          "ticketId",
          "userId"
        ],
        "type": "object",
        "properties": {
          "id": {
            "type": "integer",
            "format": "int32"
          },
          "ticketId": {
            "type": "integer",
            "format": "int32"
          },
          "ticket": {
            "$ref": "#/components/schemas/Ticket"
          },
          "content": {
            "minLength": 1,
            "type": "string"
          },
          "userId": {
            "type": "integer",
            "format": "int32"
          },
          "user": {
            "$ref": "#/components/schemas/User"
          },
          "createdAt": {
            "type": "string",
            "format": "date-time"
          },
          "updatedAt": {
            "type": "string",
            "format": "date-time",
            "nullable": true
          }
        },
        "additionalProperties": false
      },
      "UpdateAddonResponse": {
        "type": "object",
        "properties": {
          "message": {
            "type": "string",
            "nullable": true
          },
          "addon": {
            "$ref": "#/components/schemas/AddonInfo"
          },
          "updatedAt": {
            "type": "string",
            "format": "date-time"
          }
        },
        "additionalProperties": false
      },
      "UpdateCustomerResponse": {
        "type": "object",
        "properties": {
          "message": {
            "type": "string",
            "nullable": true
          },
          "customer": {
            "$ref": "#/components/schemas/CustomerInfo"
          },
          "updatedAt": {
            "type": "string",
            "format": "date-time"
          }
        },
        "additionalProperties": false
      },
      "UpdateSaleOrderResponse": {
        "type": "object",
        "properties": {
          "message": {
            "type": "string",
            "nullable": true
          },
          "saleOrder": {
            "$ref": "#/components/schemas/SaleOrderInfo"
          },
          "updatedAt": {
            "type": "string",
            "format": "date-time"
          }
        },
        "additionalProperties": false
      },
      "UpdateServiceResponse": {
        "type": "object",
        "properties": {
          "message": {
            "type": "string",
            "nullable": true
          },
          "service": {
            "$ref": "#/components/schemas/ServiceInfo"
          },
          "updatedAt": {
            "type": "string",
            "format": "date-time"
          }
        },
        "additionalProperties": false
      },
      "UpdateTicketStatusRequest": {
        "required": [
          "status"
        ],
        "type": "object",
        "properties": {
          "status": {
            "minLength": 1,
            "type": "string"
          }
        },
        "additionalProperties": false
      },
      "UpdateUserResponse": {
        "type": "object",
        "properties": {
          "message": {
            "type": "string",
            "nullable": true
          },
          "user": {
            "$ref": "#/components/schemas/UserInfo"
          },
          "updatedAt": {
            "type": "string",
            "format": "date-time"
          }
        },
        "additionalProperties": false
      },
      "User": {
        "required": [
          "email",
          "name",
          "password"
        ],
        "type": "object",
        "properties": {
          "id": {
            "type": "integer",
            "format": "int32"
          },
          "name": {
            "maxLength": 100,
            "minLength": 0,
            "type": "string"
          },
          "email": {
            "maxLength": 150,
            "minLength": 0,
            "type": "string",
            "format": "email"
          },
          "password": {
            "maxLength": 255,
            "minLength": 0,
            "type": "string"
          },
          "position": {
            "maxLength": 100,
            "minLength": 0,
            "type": "string",
            "nullable": true
          },
          "phoneNumber": {
            "maxLength": 20,
            "minLength": 0,
            "type": "string",
            "nullable": true
          },
          "address": {
            "maxLength": 500,
            "minLength": 0,
            "type": "string",
            "nullable": true
          },
          "role": {
            "maxLength": 50,
            "minLength": 0,
            "type": "string",
            "nullable": true
          },
          "secondaryEmail": {
            "maxLength": 150,
            "minLength": 0,
            "type": "string",
            "format": "email",
            "nullable": true
          },
          "createdAt": {
            "type": "string",
            "format": "date-time"
          },
          "updatedAt": {
            "type": "string",
            "format": "date-time",
            "nullable": true
          }
        },
        "additionalProperties": false
      },
      "UserInfo": {
        "type": "object",
        "properties": {
          "id": {
            "type": "integer",
            "format": "int32"
          },
          "name": {
            "type": "string",
            "nullable": true
          },
          "email": {
            "type": "string",
            "nullable": true
          },
          "position": {
            "type": "string",
            "nullable": true
          },
          "role": {
            "type": "string",
            "nullable": true
          }
        },
        "additionalProperties": false
      }
    },
    "securitySchemes": {
      "Bearer": {
        "type": "apiKey",
        "description": "JWT Authorization header using the Bearer scheme. Example: \"Authorization: Bearer {token}\"",
        "name": "Authorization",
        "in": "header"
      }
    }
  },
  "security": [
    {
      "Bearer": [ ]
    }
  ]
}